MANIFEST.in
README.rst
setup.py
aliyun_python_sdk_crm.egg-info/PKG-INFO
aliyun_python_sdk_crm.egg-info/SOURCES.txt
aliyun_python_sdk_crm.egg-info/dependency_links.txt
aliyun_python_sdk_crm.egg-info/requires.txt
aliyun_python_sdk_crm.egg-info/top_level.txt
aliyunsdkcrm/__init__.py
aliyunsdkcrm/request/__init__.py
aliyunsdkcrm/request/v20150408/AddIdentityCertifiedForBidUserRequest.py
aliyunsdkcrm/request/v20150408/AddLabelForBidRequest.py
aliyunsdkcrm/request/v20150408/AddLabelRequest.py
aliyunsdkcrm/request/v20150408/BatchGetAliyunIdByAliyunPkRequest.py
aliyunsdkcrm/request/v20150408/CheckLabelForBidRequest.py
aliyunsdkcrm/request/v20150408/CheckLabelRequest.py
aliyunsdkcrm/request/v20150408/DeleteLabelForBidRequest.py
aliyunsdkcrm/request/v20150408/DeleteLabelRequest.py
aliyunsdkcrm/request/v20150408/GetAliyunPkByAliyunIdRequest.py
aliyunsdkcrm/request/v20150408/QueryBidUserCertifiedInfoRequest.py
aliyunsdkcrm/request/v20150408/QueryCustomerLabelRequest.py
aliyunsdkcrm/request/v20150408/RemoveIdentityCertifiedForBidUserRequest.py
aliyunsdkcrm/request/v20150408/__init__.py